consilio/assemble.py
consilio/consult.py
consilio/main.py
consilio/observe.py
consilio/setup.py
consilio/utils.py
consilio-0.1.2.dist-info/LICENSE
consilio-0.1.2.dist-info/METADATA
consilio-0.1.2.dist-info/WHEEL
consilio-0.1.2.dist-info/entry_points.txt
consilio-0.1.2.dist-info/top_level.txt
consilio-0.1.2.dist-info/RECORD
