Metadata-Version: 2.1
Name: consilio
Version: 0.1.2
Summary: A Personal Decision Making Tool powered by LLMs
Author-email: Alex Dong <me@alexdong.com>
Project-URL: Homepage, https://github.com/yourusername/consilio
Project-URL: Bug Tracker, https://github.com/yourusername/consilio/issues
Classifier: Programming Language :: Python :: 3
Classifier: License :: OSI Approved :: MIT License
Classifier: Operating System :: OS Independent
Requires-Python: >=3.11
License-File: LICENSE
Requires-Dist: anthropic>=0.8.0
Requires-Dist: better-exceptions>=0.3.3
Requires-Dist: prompt-toolkit>=3.0.0
Requires-Dist: PyYAML>=6.0.1
Requires-Dist: Jinja2>=3.1.0
Requires-Dist: python-slugify>=8.0.1
Provides-Extra: dev
Requires-Dist: ruff>=0.1.9; extra == "dev"
Requires-Dist: twine>=4.0.2; extra == "dev"
Requires-Dist: build>=1.0.3; extra == "dev"
